minml/__init__.py
minml/strings.py
minml-0.0.1.dist-info/METADATA
minml-0.0.1.dist-info/WHEEL
minml-0.0.1.dist-info/top_level.txt
minml-0.0.1.dist-info/RECORD
