Metadata-Version: 2.1
Name: minml
Version: 0.0.1
Summary: Remove the yammering from LLM outputs.
Author-email: Hudson Cooper <hmncooper96@gmail.com>
Project-URL: source, https://github.com/hudson-ai
Project-URL: download, https://pypi.org/project/minml/#files
Requires-Dist: pyparsing
Requires-Dist: pytest
